{
    "workbench.colorCustomizations": {
        "terminal.foreground": "#fcfcfa",
        "terminal.background": "#262427",
        "terminal.ansiBlack": "#262427",
        "terminal.ansiBlue": "#49cae4",
        "terminal.ansiCyan": "#aee8f4",
        "terminal.ansiGreen": "#bcdf59",
        "terminal.ansiMagenta": "#a093e2",
        "terminal.ansiRed": "#ff7272",
        "terminal.ansiWhite": "#fcfcfa",
        "terminal.ansiYellow": "#ffca58",
        "terminal.ansiBrightBlack": "#545452",
        "terminal.ansiBrightBlue": "#64d2e8",
        "terminal.ansiBrightCyan": "#baebf6",
        "terminal.ansiBrightGreen": "#c6e472",
        "terminal.ansiBrightMagenta": "#aea3e6",
        "terminal.ansiBrightRed": "#ff8787",
        "terminal.ansiBrightWhite": "#fcfcfa",
        "terminal.ansiBrightYellow": "#ffd271",
        "terminal.selectionBackground": "#fcfcfa",
        "terminalCursor.background": "#000000",
        "terminalCursor.foreground": "#fcfcfa"
    }
}
