{
    "workbench.colorCustomizations": {
        "terminal.foreground": "#d0d0d0",
        "terminal.background": "#212121",
        "terminal.ansiBlack": "#151515",
        "terminal.ansiBlue": "#6c99bb",
        "terminal.ansiCyan": "#7dd6cf",
        "terminal.ansiGreen": "#7e8e50",
        "terminal.ansiMagenta": "#9f4e85",
        "terminal.ansiRed": "#ac4142",
        "terminal.ansiWhite": "#d0d0d0",
        "terminal.ansiYellow": "#e5b567",
        "terminal.ansiBrightBlack": "#505050",
        "terminal.ansiBrightBlue": "#6c99bb",
        "terminal.ansiBrightCyan": "#7dd6cf",
        "terminal.ansiBrightGreen": "#7e8e50",
        "terminal.ansiBrightMagenta": "#9f4e85",
        "terminal.ansiBrightRed": "#ac4142",
        "terminal.ansiBrightWhite": "#f5f5f5",
        "terminal.ansiBrightYellow": "#e5b567",
        "terminal.selectionBackground": "#303030",
        "terminalCursor.foreground": "#d0d0d0"
    }
}
