{
    "workbench.colorCustomizations": {
        "terminal.foreground": "#e0def4",
        "terminal.background": "#232136",
        "terminal.ansiBlack": "#393552",
        "terminal.ansiBlue": "#569fba",
        "terminal.ansiCyan": "#9ccfd8",
        "terminal.ansiGreen": "#a3be8c",
        "terminal.ansiMagenta": "#c4a7e7",
        "terminal.ansiRed": "#eb6f92",
        "terminal.ansiWhite": "#e0def4",
        "terminal.ansiYellow": "#f6c177",
        "terminal.ansiBrightBlack": "#544d8a",
        "terminal.ansiBrightBlue": "#65b1cd",
        "terminal.ansiBrightCyan": "#a6dae3",
        "terminal.ansiBrightGreen": "#b1d196",
        "terminal.ansiBrightMagenta": "#ccb1ed",
        "terminal.ansiBrightRed": "#f083a2",
        "terminal.ansiBrightWhite": "#e2e0f7",
        "terminal.ansiBrightYellow": "#f9cb8c",
        "terminal.selectionBackground": "#433c59",
        "terminalCursor.background": "#232136",
        "terminalCursor.foreground": "#e0def4"
    }
}
