{
    "workbench.colorCustomizations": {
        "terminal.foreground": "#303030",
        "terminal.background": "#fafaff",
        "terminal.ansiBlack": "#303030",
        "terminal.ansiBlue": "#006cd8",
        "terminal.ansiCyan": "#00798a",
        "terminal.ansiGreen": "#0a7f3d",
        "terminal.ansiMagenta": "#583cac",
        "terminal.ansiRed": "#a31700",
        "terminal.ansiWhite": "#303030",
        "terminal.ansiYellow": "#af551d",
        "terminal.ansiBrightBlack": "#303030",
        "terminal.ansiBrightBlue": "#006cd8",
        "terminal.ansiBrightCyan": "#00798a",
        "terminal.ansiBrightGreen": "#0a7f3d",
        "terminal.ansiBrightMagenta": "#583cac",
        "terminal.ansiBrightRed": "#a31700",
        "terminal.ansiBrightWhite": "#303030",
        "terminal.ansiBrightYellow": "#af551d",
        "terminal.selectionBackground": "#ad95e9",
        "terminalCursor.background": "#303030",
        "terminalCursor.foreground": "#303030"
    }
}
