{
    "workbench.colorCustomizations": {
        "terminal.foreground": "#16b10e",
        "terminal.background": "#020f01",
        "terminal.ansiBlack": "#001f0b",
        "terminal.ansiBlue": "#15d00d",
        "terminal.ansiCyan": "#15d00d",
        "terminal.ansiGreen": "#15d00d",
        "terminal.ansiMagenta": "#15d00d",
        "terminal.ansiRed": "#15d00d",
        "terminal.ansiWhite": "#fafafa",
        "terminal.ansiYellow": "#15d00d",
        "terminal.ansiBrightBlack": "#001510",
        "terminal.ansiBrightBlue": "#19e20e",
        "terminal.ansiBrightCyan": "#19e20e",
        "terminal.ansiBrightGreen": "#19e20e",
        "terminal.ansiBrightMagenta": "#19e20e",
        "terminal.ansiBrightRed": "#19e20e",
        "terminal.ansiBrightWhite": "#fefefe",
        "terminal.ansiBrightYellow": "#19e20e",
        "terminal.selectionBackground": "#d4ffc1",
        "terminalCursor.foreground": "#15d00d"
    }
}
