{
    "workbench.colorCustomizations": {
        "terminal.foreground": "#ffffff",
        "terminal.background": "#ea3323",
        "terminal.ansiBlack": "#000000",
        "terminal.ansiBlue": "#000000",
        "terminal.ansiCyan": "#ffffff",
        "terminal.ansiGreen": "#ffff54",
        "terminal.ansiMagenta": "#ffff54",
        "terminal.ansiRed": "#ffff54",
        "terminal.ansiWhite": "#c6c6c6",
        "terminal.ansiYellow": "#ffff54",
        "terminal.ansiBrightBlack": "#000000",
        "terminal.ansiBrightBlue": "#000000",
        "terminal.ansiBrightCyan": "#ffffff",
        "terminal.ansiBrightGreen": "#ffff54",
        "terminal.ansiBrightMagenta": "#ffff54",
        "terminal.ansiBrightRed": "#ffff54",
        "terminal.ansiBrightWhite": "#c6c6c6",
        "terminal.ansiBrightYellow": "#ffff54",
        "terminal.selectionBackground": "#ffff54",
        "terminalCursor.background": "#ffffff",
        "terminalCursor.foreground": "#ffff54"
    }
}
