{
    "workbench.colorCustomizations": {
        "terminal.foreground": "#cac296",
        "terminal.background": "#1d1908",
        "terminal.ansiBlack": "#000000",
        "terminal.ansiBlue": "#616bb0",
        "terminal.ansiCyan": "#916c25",
        "terminal.ansiGreen": "#7c8b16",
        "terminal.ansiMagenta": "#8c5a90",
        "terminal.ansiRed": "#b64c00",
        "terminal.ansiWhite": "#cac29a",
        "terminal.ansiYellow": "#d3bd26",
        "terminal.ansiBrightBlack": "#5e5219",
        "terminal.ansiBrightBlue": "#acb8ff",
        "terminal.ansiBrightCyan": "#ffbc51",
        "terminal.ansiBrightGreen": "#b2ca3b",
        "terminal.ansiBrightMagenta": "#ffa0ff",
        "terminal.ansiBrightRed": "#ff9149",
        "terminal.ansiBrightWhite": "#fed698",
        "terminal.ansiBrightYellow": "#ffe54a",
        "terminal.selectionBackground": "#626dac",
        "terminalCursor.foreground": "#d3ba30"
    }
}
