{
    "workbench.colorCustomizations": {
        "terminal.foreground": "#e0e2ea",
        "terminal.background": "#14161b",
        "terminal.ansiBlack": "#07080d",
        "terminal.ansiBlue": "#a6dbff",
        "terminal.ansiCyan": "#8cf8f7",
        "terminal.ansiGreen": "#b3f6c0",
        "terminal.ansiMagenta": "#ffcaff",
        "terminal.ansiRed": "#ffc0b9",
        "terminal.ansiWhite": "#eef1f8",
        "terminal.ansiYellow": "#fce094",
        "terminal.ansiBrightBlack": "#4f5258",
        "terminal.ansiBrightBlue": "#a6dbff",
        "terminal.ansiBrightCyan": "#8cf8f7",
        "terminal.ansiBrightGreen": "#b3f6c0",
        "terminal.ansiBrightMagenta": "#ffcaff",
        "terminal.ansiBrightRed": "#ffc0b9",
        "terminal.ansiBrightWhite": "#eef1f8",
        "terminal.ansiBrightYellow": "#fce094",
        "terminal.selectionBackground": "#4f5258",
        "terminalCursor.foreground": "#9b9ea4"
    }
}
