{
    "workbench.colorCustomizations": {
        "terminal.foreground": "#ffffff",
        "terminal.background": "#1a1a1a",
        "terminal.ansiBlack": "#000000",
        "terminal.ansiBlue": "#56c2ff",
        "terminal.ansiCyan": "#52eee5",
        "terminal.ansiGreen": "#59d499",
        "terminal.ansiMagenta": "#cf2f98",
        "terminal.ansiRed": "#ff5360",
        "terminal.ansiWhite": "#ffffff",
        "terminal.ansiYellow": "#ffc531",
        "terminal.ansiBrightBlack": "#000000",
        "terminal.ansiBrightBlue": "#56c2ff",
        "terminal.ansiBrightCyan": "#52eee5",
        "terminal.ansiBrightGreen": "#59d499",
        "terminal.ansiBrightMagenta": "#cf2f98",
        "terminal.ansiBrightRed": "#ff6363",
        "terminal.ansiBrightWhite": "#ffffff",
        "terminal.ansiBrightYellow": "#ffc531",
        "terminal.selectionBackground": "#333333",
        "terminalCursor.foreground": "#cccccc"
    }
}
