{
    "workbench.colorCustomizations": {
        "terminal.foreground": "#282930",
        "terminal.background": "#edeef2",
        "terminal.ansiBlack": "#d4d5dc",
        "terminal.ansiBlue": "#5f6370",
        "terminal.ansiCyan": "#454752",
        "terminal.ansiGreen": "#2e3038",
        "terminal.ansiMagenta": "#25262d",
        "terminal.ansiRed": "#525666",
        "terminal.ansiWhite": "#282930",
        "terminal.ansiYellow": "#50535e",
        "terminal.ansiBrightBlack": "#42434e",
        "terminal.ansiBrightBlue": "#5f6370",
        "terminal.ansiBrightCyan": "#454752",
        "terminal.ansiBrightGreen": "#2e3038",
        "terminal.ansiBrightMagenta": "#25262d",
        "terminal.ansiBrightRed": "#525666",
        "terminal.ansiBrightWhite": "#282930",
        "terminal.ansiBrightYellow": "#50535e",
        "terminal.selectionBackground": "#817c9c",
        "terminalCursor.background": "#282930",
        "terminalCursor.foreground": "#565760"
    }
}
