{
    "workbench.colorCustomizations": {
        "terminal.foreground": "#708284",
        "terminal.background": "#001e27",
        "terminal.ansiBlack": "#002831",
        "terminal.ansiBlue": "#2176c7",
        "terminal.ansiCyan": "#259286",
        "terminal.ansiGreen": "#738a05",
        "terminal.ansiMagenta": "#c61c6f",
        "terminal.ansiRed": "#d11c24",
        "terminal.ansiWhite": "#eae3cb",
        "terminal.ansiYellow": "#a57706",
        "terminal.ansiBrightBlack": "#475b62",
        "terminal.ansiBrightBlue": "#708284",
        "terminal.ansiBrightCyan": "#819090",
        "terminal.ansiBrightGreen": "#475b62",
        "terminal.ansiBrightMagenta": "#5956ba",
        "terminal.ansiBrightRed": "#bd3613",
        "terminal.ansiBrightWhite": "#fcf4dc",
        "terminal.ansiBrightYellow": "#536870",
        "terminal.selectionBackground": "#002831",
        "terminalCursor.foreground": "#708284"
    }
}
